LICENSE
MANIFEST.in
README
README.md
setup.py
bin/drawm
docs/readme.txt
drawm/VERSION
drawm/__init__.py
drawm/common.py
drawm/draw_tree.py
drawm/main.py
drawm.egg-info/PKG-INFO
drawm.egg-info/SOURCES.txt
drawm.egg-info/dependency_links.txt
drawm.egg-info/requires.txt
drawm.egg-info/top_level.txt
drawm/svg/__init__.py
drawm/svg/bootstrap_props.py
drawm/svg/contour_props.py
drawm/svg/geometry.py
drawm/svg/label_props.py
drawm/svg/lineage_props.py
drawm/svg/svg_utils.py
drawm/svg/tree_props.py
drawm/tree/__init__.py
drawm/tree/newick_utils.py
drawm/tree/prune.py
drawm/tree/rename.py
drawm/tree/reroot.py
drawm/tree/subtree.py
drawm/tree/tree_utils.py