Metadata-Version: 1.0
Name: drawm
Version: 0.0.2
Summary: A toolkit for creating publication-quality images of phylogenetic trees.
Home-page: http://pypi.python.org/pypi/drawm/
Author: Donovan Parks
Author-email: donovan.parks@gmail.com
License: GPL3
Platform: UNKNOWN
